test/cut01/cut01.vhd
library ieee;
use ieee.std_logic_1164.all;
-- USE IEEE.std_logic_arith.all;

entity cut01 is
    port(
        input_vector    : in std_logic_vector(7 downto 0);
        output_vector   : out std_logic_vector(1 downto 0)
    );
end cut01;

architecture rtl of cut01 is
    signal s0 : std_logic_vector(7 downto 0);
    signal s1 : std_logic_vector(2 downto 0);
    signal s2 : std_logic_vector(2 downto 0);
begin

    s0(0) <= input_vector(0);
    s0(1) <= input_vector(1);
    s0(2) <= input_vector(2);
    s0(3) <= input_vector(3);
    s0(4) <= input_vector(4);
    s0(5) <= input_vector(5);
    s0(6) <= input_vector(6);
    s0(7) <= input_vector(7);

    s1(0) <= s0(0) or s0(1);
    s1(1) <= s0(3) or s0(4);
    s1(2) <= s0(5) xor s0(6);
    
    s2(0) <= s1(1) and s0(2);
    s2(1) <= s2(0);
    s2(2) <= s1(2) or s0(7); 

    output_vector(0) <= s2(0) and s1(0);
    output_vector(1) <= s2(1) xor s2(2);

end architecture;

test/cut01/tb_cut01.vhd
library ieee;
use ieee.std_logic_1164.all;

entity tb_cut01 is

end tb_cut01;

architecture rtl of tb_cut01 is

    constant T : time := 20 us;

    procedure wait_cycles(n : natural) is
    begin
        for i in 0 to n-1 loop
            wait for T;
        end loop; 
    end procedure;

    procedure wait1 is
    begin
        wait for T;
    end procedure;

    signal tb_input_vector : std_logic_vector(7 downto 0) := "00000000";
    signal tb_output_vector : std_logic_vector(1 downto 0);
begin

    UUT : entity work.cut01
    port map (
        input_vector => tb_input_vector,
        output_vector => tb_output_vector
    );

    process 
    begin

        report "Starting test simulation ...";
        report "Incremental by one";
        wait1;
        tb_input_vector <= "00000001";

        wait1;
        tb_input_vector <= "00000010";

        wait1;
        tb_input_vector <= "00000011";

        wait1;
        tb_input_vector <= "00000100";

        report "Multiplied by two";
        wait1;
        tb_input_vector <= "00001000";

        wait1;
        tb_input_vector <= "00010000";

        wait1;
        tb_input_vector <= "00100000";

        wait1;
        tb_input_vector <= "01000000";

        report "Checkerboard";
        wait1;
        tb_input_vector <= "01010101";

        wait1;
        tb_input_vector <= "10101010";

        wait1;
        tb_input_vector <= "01010101";

        wait1;
        tb_input_vector <= "10101010";

        report "Simulation terminated";

        wait;
    end process;

end architecture;

test/cut01/sim_cut01.vcd
$date
  Thu Feb  9 10:30:38 2023
$end
$version
  GHDL v0
$end
$timescale
  1 fs
$end
$scope module standard $end
$upscope $end
$scope module std_logic_1164 $end
$upscope $end
$scope module tb_cut01 $end
$var reg 8 ! tb_input_vector[7:0] $end
$var reg 2 " tb_output_vector[1:0] $end
$scope module uut $end
$var reg 8 # input_vector[7:0] $end
$var reg 2 $ output_vector[1:0] $end
$var reg 8 % s0[7:0] $end
$var reg 3 & s1[2:0] $end
$var reg 3 ' s2[2:0] $end
$upscope $end
$upscope $end
$enddefinitions $end
#0
b00000000 !
b00 "
b00000000 #
b00 $
b00000000 %
b000 &
b000 '
#20000000000
b00000001 !
b00000001 #
b00000001 %
b001 &
#40000000000
b00000010 !
b00000010 #
b00000010 %
#60000000000
b00000011 !
b00000011 #
b00000011 %
#80000000000
b00000100 !
b00000100 #
b00000100 %
b000 &
#100000000000
b00001000 !
b00001000 #
b00001000 %
#120000000000
b00010000 !
b00010000 #
b00010000 %
#140000000000
b00100000 !
b10 "
b00100000 #
b10 $
b00100000 %
b100 &
b100 '
#160000000000
b01000000 !
b01000000 #
b01000000 %
#180000000000
b01010101 !
b01010101 #
b01010101 %
b101 &
#200000000000
b10101010 !
b10101010 #
b10101010 %
#220000000000
b01010101 !
b01010101 #
b01010101 %
#240000000000
b10101010 !
b10101010 #
b10101010 %
